{
  "07f260f4-466c-4607-9a33-f7273b24f1b4": {
      "_id": "07f260f4-466c-4607-9a33-f7273b24f1b4",
      "firstName": "Благой",
      "lastName": "Благов",
      "email": "blagoicho0@gmail.com",
      "phoneNumber": "0899999999",
      "password": "",
      "location": "Благоевград",
      "createdAt": "2023-11-01T07:22:00.358Z",
      "updatedAt": "2023-11-01T07:22:00.358Z",
      "imageUrl": "https://fit.bbweb.dev/wp-content/uploads/listing-uploads/logo/2023/09/profile.jpg"
  },
  "6d0fa592-580e-47ce-9b95-8cc1820c5845": {
      "firstName": "Борислав",
      "lastName": "Янаков",
      "email": "bob@gmail.com",
      "phoneNumber": "089999219",
      "password": "",
      "location": "София",
      "createdAt": "2023-11-01T07:22:00.358Z",
      "updatedAt": "2023-11-01T07:22:00.358Z",
      "imageUrl": "https://fit.bbweb.dev/wp-content/uploads/listing-uploads/logo/2023/09/fdecd6bd8d3d1447b1cf38d599430b27.jpg",
      "_id": "6d0fa592-580e-47ce-9b95-8cc1820c5845"
  }
}